fastagency/__about__.py
fastagency/__init__.py
fastagency/__main__.py
fastagency/app.py
fastagency/base.py
fastagency/exceptions.py
fastagency/helpers.py
fastagency/logging.py
fastagency/messages.py
fastagency/adapters/__init__.py
fastagency/adapters/awp/__init__.py
fastagency/adapters/awp/base.py
fastagency/adapters/awp/tryrun.py
fastagency/adapters/fastapi/__init__.py
fastagency/adapters/fastapi/base.py
fastagency/adapters/nats/__init__.py
fastagency/adapters/nats/base.py
fastagency/api/__init__.py
fastagency/api/dependency_injection.py
fastagency/api/openapi/__init__.py
fastagency/api/openapi/fastapi_code_generator_helpers.py
fastagency/api/openapi/openapi.py
fastagency/api/openapi/patch_datamodel_code_generator.py
fastagency/api/openapi/patch_fastapi_code_generator.py
fastagency/api/openapi/security.py
fastagency/api/openapi/security_schema_visitor.py
fastagency/cli/__init__.py
fastagency/cli/cli.py
fastagency/cli/discover.py
fastagency/cli/docker_cli.py
fastagency/cli/logging.py
fastagency/runtimes/__init__.py
fastagency/runtimes/ag2/__init__.py
fastagency/runtimes/ag2/ag2.py
fastagency/runtimes/ag2/agents/__init__.py
fastagency/runtimes/ag2/agents/websurfer.py
fastagency/runtimes/ag2/agents/whatsapp.py
fastagency/runtimes/ag2/tools/__init__.py
fastagency/runtimes/ag2/tools/websurfer.py
fastagency/runtimes/ag2/tools/whatsapp.py
fastagency/ui/__init__.py
fastagency/ui/console/__init__.py
fastagency/ui/console/console.py
fastagency/ui/mesop/__init__.py
fastagency/ui/mesop/data_model.py
fastagency/ui/mesop/main.py
fastagency/ui/mesop/mesop.py
fastagency/ui/mesop/message.py
fastagency/ui/mesop/send_prompt.py
fastagency/ui/mesop/styles.py
fastagency/ui/mesop/timer.py
fastagency/ui/mesop/auth/__init__.py
fastagency/ui/mesop/auth/auth.py
fastagency/ui/mesop/auth/basic_auth/__init__.py
fastagency/ui/mesop/auth/basic_auth/basic_auth.py
fastagency/ui/mesop/auth/basic_auth/basic_auth_component.py
fastagency/ui/mesop/auth/firebase/__init__.py
fastagency-0.9.9.dist-info/METADATA
fastagency-0.9.9.dist-info/WHEEL
fastagency-0.9.9.dist-info/entry_points.txt
fastagency-0.9.9.dist-info/licenses/LICENSE
fastagency-0.9.9.dist-info/RECORD
