Metadata-Version: 2.4
Name: fastagency
Version: 0.9.9
Summary: The fastest way to bring multi-agent workflows to production
Project-URL: Homepage, https://github.com/ag2ai/fastagency
Project-URL: Documentation, https://fastagency.ai/latest/
Project-URL: Tracker, https://github.com/ag2ai/fastagency/issues
Project-URL: Source, https://github.com/ag2ai/fastagency
Project-URL: Discord, https://discord.gg/kJjSGWrknU
Author-email: ag2ai <support@ag2.ai>
License-File: LICENSE
Keywords: AI,LLM,ag2,autogen,autonomous agents,multi-agent
Classifier: Development Status :: 4 - Beta
Classifier: Environment :: Web Environment
Classifier: Framework :: AsyncIO
Classifier: Framework :: Pydantic
Classifier: Framework :: Pydantic :: 2
Classifier: Intended Audience :: Developers
Classifier: Intended Audience :: Information Technology
Classifier: Intended Audience :: System Administrators
Classifier: License :: OSI Approved :: Apache Software License
Classifier: Operating System :: OS Independent
Classifier: Programming Language :: Python
Classifier: Programming Language :: Python :: 3
Classifier: Programming Language :: Python :: 3 :: Only
Classifier: Programming Language :: Python :: 3.10
Classifier: Programming Language :: Python :: 3.11
Classifier: Programming Language :: Python :: 3.12
Classifier: Programming Language :: Python :: Implementation :: CPython
Classifier: Topic :: Internet
Classifier: Topic :: Software Development
Classifier: Topic :: Software Development :: Libraries
Classifier: Topic :: Software Development :: Libraries :: Application Frameworks
Classifier: Topic :: Software Development :: Libraries :: Python Modules
Classifier: Typing :: Typed
Requires-Python: >=3.10
Requires-Dist: ag2==0.9.9
Requires-Dist: click==8.1.3
Requires-Dist: markdownify==0.14.1
Requires-Dist: pydantic<3,>=2.2.0
Requires-Dist: typer!=0.15.3,>=0.12.5
Requires-Dist: typing-extensions<5,>=4.8.0
Provides-Extra: basic-auth
Requires-Dist: bcrypt>=4.2.0; extra == 'basic-auth'
Provides-Extra: copilotkit
Requires-Dist: agentwire==0.1.4; extra == 'copilotkit'
Provides-Extra: dev
Requires-Dist: ag2[openai,websurfer]; extra == 'dev'
Requires-Dist: ag2[openai]; extra == 'dev'
Requires-Dist: agentwire==0.1.4; extra == 'dev'
Requires-Dist: asyncer==0.0.8; extra == 'dev'
Requires-Dist: bandit==1.8.3; extra == 'dev'
Requires-Dist: bcrypt>=4.2.0; extra == 'dev'
Requires-Dist: cairosvg==2.7.1; extra == 'dev'
Requires-Dist: codespell==2.4.1; extra == 'dev'
Requires-Dist: cookiecutter==2.6.0; extra == 'dev'
Requires-Dist: coverage[toml]==7.7.0; extra == 'dev'
Requires-Dist: detect-secrets==1.5.0; extra == 'dev'
Requires-Dist: dirty-equals==0.9.0; extra == 'dev'
Requires-Dist: email-validator==2.2.0; extra == 'dev'
Requires-Dist: fastapi-code-generator==0.5.2; extra == 'dev'
Requires-Dist: fastapi<1,>=0.112; extra == 'dev'
Requires-Dist: faststream[nats]<0.6,>=0.5.27; extra == 'dev'
Requires-Dist: firebase-admin>=6.5.0; extra == 'dev'
Requires-Dist: griffe<1.6.0; extra == 'dev'
Requires-Dist: gunicorn>=23.0.0; (platform_system != 'Windows') and extra == 'dev'
Requires-Dist: jsondiff==2.2.1; extra == 'dev'
Requires-Dist: mdx-include==1.4.2; extra == 'dev'
Requires-Dist: mesop<1,>=0.12.7; (python_version >= '3.10') and extra == 'dev'
Requires-Dist: mike==2.1.3; extra == 'dev'
Requires-Dist: mkdocs-autorefs==1.2.0; extra == 'dev'
Requires-Dist: mkdocs-git-revision-date-localized-plugin==1.3.0; extra == 'dev'
Requires-Dist: mkdocs-glightbox==0.4.0; extra == 'dev'
Requires-Dist: mkdocs-literate-nav==0.6.1; extra == 'dev'
Requires-Dist: mkdocs-macros-plugin==1.3.7; extra == 'dev'
Requires-Dist: mkdocs-material==9.5.48; extra == 'dev'
Requires-Dist: mkdocs-minify-plugin==0.8.0; extra == 'dev'
Requires-Dist: mkdocs-static-i18n==1.2.3; extra == 'dev'
Requires-Dist: mkdocs==1.6.1; extra == 'dev'
Requires-Dist: mkdocstrings[python]==0.27.0; extra == 'dev'
Requires-Dist: mypy==1.15.0; extra == 'dev'
Requires-Dist: passlib[bcrypt]==1.7.4; extra == 'dev'
Requires-Dist: pillow<11,==10.4.0; extra == 'dev'
Requires-Dist: pre-commit==4.1.0; extra == 'dev'
Requires-Dist: pydantic-settings==2.8.1; extra == 'dev'
Requires-Dist: pyjwt==2.10.0; extra == 'dev'
Requires-Dist: pytest-asyncio==0.25.3; extra == 'dev'
Requires-Dist: pytest-mypy-plugins==3.2.0; extra == 'dev'
Requires-Dist: pytest-rerunfailures==15.0; extra == 'dev'
Requires-Dist: pytest==8.3.5; extra == 'dev'
Requires-Dist: python-multipart>=0.0.20; extra == 'dev'
Requires-Dist: pyyaml==6.0.2; extra == 'dev'
Requires-Dist: requests; extra == 'dev'
Requires-Dist: ruff==0.11.0; extra == 'dev'
Requires-Dist: semgrep==1.112.0; extra == 'dev'
Requires-Dist: types-docutils; extra == 'dev'
Requires-Dist: types-pygments; extra == 'dev'
Requires-Dist: types-pyyaml; extra == 'dev'
Requires-Dist: types-setuptools; extra == 'dev'
Requires-Dist: types-ujson; extra == 'dev'
Requires-Dist: uvicorn>=0.31.0; extra == 'dev'
Requires-Dist: waitress>=3.0.0; (platform_system == 'Windows') and extra == 'dev'
Requires-Dist: watchfiles==1.0.4; extra == 'dev'
Requires-Dist: websockets<14,>=13; extra == 'dev'
Provides-Extra: devdocs
Requires-Dist: cairosvg==2.7.1; extra == 'devdocs'
Requires-Dist: cookiecutter==2.6.0; extra == 'devdocs'
Requires-Dist: griffe<1.6.0; extra == 'devdocs'
Requires-Dist: mdx-include==1.4.2; extra == 'devdocs'
Requires-Dist: mike==2.1.3; extra == 'devdocs'
Requires-Dist: mkdocs-autorefs==1.2.0; extra == 'devdocs'
Requires-Dist: mkdocs-git-revision-date-localized-plugin==1.3.0; extra == 'devdocs'
Requires-Dist: mkdocs-glightbox==0.4.0; extra == 'devdocs'
Requires-Dist: mkdocs-literate-nav==0.6.1; extra == 'devdocs'
Requires-Dist: mkdocs-macros-plugin==1.3.7; extra == 'devdocs'
Requires-Dist: mkdocs-material==9.5.48; extra == 'devdocs'
Requires-Dist: mkdocs-minify-plugin==0.8.0; extra == 'devdocs'
Requires-Dist: mkdocs-static-i18n==1.2.3; extra == 'devdocs'
Requires-Dist: mkdocs==1.6.1; extra == 'devdocs'
Requires-Dist: mkdocstrings[python]==0.27.0; extra == 'devdocs'
Requires-Dist: pillow<11,==10.4.0; extra == 'devdocs'
Provides-Extra: fastapi
Requires-Dist: asyncer==0.0.8; extra == 'fastapi'
Requires-Dist: fastapi<1,>=0.112; extra == 'fastapi'
Requires-Dist: websockets<14,>=13; extra == 'fastapi'
Provides-Extra: firebase
Requires-Dist: firebase-admin>=6.5.0; extra == 'firebase'
Provides-Extra: lint
Requires-Dist: bandit==1.8.3; extra == 'lint'
Requires-Dist: codespell==2.4.1; extra == 'lint'
Requires-Dist: mypy==1.15.0; extra == 'lint'
Requires-Dist: pytest-mypy-plugins==3.2.0; extra == 'lint'
Requires-Dist: ruff==0.11.0; extra == 'lint'
Requires-Dist: semgrep==1.112.0; extra == 'lint'
Requires-Dist: types-docutils; extra == 'lint'
Requires-Dist: types-pygments; extra == 'lint'
Requires-Dist: types-pyyaml; extra == 'lint'
Requires-Dist: types-setuptools; extra == 'lint'
Requires-Dist: types-ujson; extra == 'lint'
Provides-Extra: mesop
Requires-Dist: mesop<1,>=0.12.7; (python_version >= '3.10') and extra == 'mesop'
Provides-Extra: nats
Requires-Dist: asyncer==0.0.8; extra == 'nats'
Requires-Dist: fastapi<1,>=0.112; extra == 'nats'
Requires-Dist: faststream[nats]<0.6,>=0.5.27; extra == 'nats'
Requires-Dist: websockets<14,>=13; extra == 'nats'
Provides-Extra: openai
Requires-Dist: ag2[openai]; extra == 'openai'
Provides-Extra: openapi
Requires-Dist: fastapi-code-generator==0.5.2; extra == 'openapi'
Requires-Dist: fastapi<1,>=0.112; extra == 'openapi'
Requires-Dist: requests; extra == 'openapi'
Provides-Extra: server
Requires-Dist: gunicorn>=23.0.0; (platform_system != 'Windows') and extra == 'server'
Requires-Dist: uvicorn>=0.31.0; extra == 'server'
Requires-Dist: waitress>=3.0.0; (platform_system == 'Windows') and extra == 'server'
Provides-Extra: submodules
Requires-Dist: ag2[openai]; extra == 'submodules'
Requires-Dist: agentwire==0.1.4; extra == 'submodules'
Requires-Dist: asyncer==0.0.8; extra == 'submodules'
Requires-Dist: bcrypt>=4.2.0; extra == 'submodules'
Requires-Dist: fastapi-code-generator==0.5.2; extra == 'submodules'
Requires-Dist: fastapi<1,>=0.112; extra == 'submodules'
Requires-Dist: faststream[nats]<0.6,>=0.5.27; extra == 'submodules'
Requires-Dist: firebase-admin>=6.5.0; extra == 'submodules'
Requires-Dist: gunicorn>=23.0.0; (platform_system != 'Windows') and extra == 'submodules'
Requires-Dist: mesop<1,>=0.12.7; (python_version >= '3.10') and extra == 'submodules'
Requires-Dist: requests; extra == 'submodules'
Requires-Dist: uvicorn>=0.31.0; extra == 'submodules'
Requires-Dist: waitress>=3.0.0; (platform_system == 'Windows') and extra == 'submodules'
Requires-Dist: websockets<14,>=13; extra == 'submodules'
Provides-Extra: test-core
Requires-Dist: coverage[toml]==7.7.0; extra == 'test-core'
Requires-Dist: dirty-equals==0.9.0; extra == 'test-core'
Requires-Dist: jsondiff==2.2.1; extra == 'test-core'
Requires-Dist: pytest-asyncio==0.25.3; extra == 'test-core'
Requires-Dist: pytest-rerunfailures==15.0; extra == 'test-core'
Requires-Dist: pytest==8.3.5; extra == 'test-core'
Provides-Extra: testing
Requires-Dist: ag2[openai,websurfer]; extra == 'testing'
Requires-Dist: ag2[openai]; extra == 'testing'
Requires-Dist: agentwire==0.1.4; extra == 'testing'
Requires-Dist: asyncer==0.0.8; extra == 'testing'
Requires-Dist: bcrypt>=4.2.0; extra == 'testing'
Requires-Dist: coverage[toml]==7.7.0; extra == 'testing'
Requires-Dist: dirty-equals==0.9.0; extra == 'testing'
Requires-Dist: email-validator==2.2.0; extra == 'testing'
Requires-Dist: fastapi-code-generator==0.5.2; extra == 'testing'
Requires-Dist: fastapi<1,>=0.112; extra == 'testing'
Requires-Dist: faststream[nats]<0.6,>=0.5.27; extra == 'testing'
Requires-Dist: firebase-admin>=6.5.0; extra == 'testing'
Requires-Dist: gunicorn>=23.0.0; (platform_system != 'Windows') and extra == 'testing'
Requires-Dist: jsondiff==2.2.1; extra == 'testing'
Requires-Dist: mesop<1,>=0.12.7; (python_version >= '3.10') and extra == 'testing'
Requires-Dist: passlib[bcrypt]==1.7.4; extra == 'testing'
Requires-Dist: pillow<11,==10.4.0; extra == 'testing'
Requires-Dist: pydantic-settings==2.8.1; extra == 'testing'
Requires-Dist: pyjwt==2.10.0; extra == 'testing'
Requires-Dist: pytest-asyncio==0.25.3; extra == 'testing'
Requires-Dist: pytest-rerunfailures==15.0; extra == 'testing'
Requires-Dist: pytest==8.3.5; extra == 'testing'
Requires-Dist: python-multipart>=0.0.20; extra == 'testing'
Requires-Dist: pyyaml==6.0.2; extra == 'testing'
Requires-Dist: requests; extra == 'testing'
Requires-Dist: uvicorn>=0.31.0; extra == 'testing'
Requires-Dist: waitress>=3.0.0; (platform_system == 'Windows') and extra == 'testing'
Requires-Dist: watchfiles==1.0.4; extra == 'testing'
Requires-Dist: websockets<14,>=13; extra == 'testing'
